[
    {
        "num":1,
        "img":"../assets/Sun.jpeg",
        "question": "Combien y a-t-il de planète ?",
        "answer1":"10",
        "answer2":"9",
        "answer3":"8",
        "answer4":"10",
        "goodAns":"9",
        "behavior":0
    },
   {
        "num":2,
        "img":"../assets/blackHole.jpg",
        "question":"Combien de temps met la lumière du soleil à nous parvenir ?",
        "answer1":"8 minutes",
        "answer2":"8 heures",
        "answer3":"8 secondes",
        "answer4":"8 jours",
        "goodAns":"8 minutes",
        "behavior":0
    },
    {
        "num":3,
        "img":"../assets/jupiter.jpg",
        "question":"Comment s'appelle la planète la plus proche de la Terre ?",
        "answer1":"Mercure",
        "answer2":"Saturne",
        "answer3":"Vénus",
        "answer4":"Mars",
        "goodAns":"Mars",
        "behavior":0
    },
    {
        "num":4,
        "img":"../assets/Mars.jpg",
        "question":"Quelle est la galaxie la plus proche de notre système solaire ?",
        "answer1":"Persée",
        "answer2":"Andromède",
        "answer3":"Coma",
        "answer4":"Chicken",
        "goodAns":"Andromède",
        "behavior":0
    },
    {
        "num":5,
        "img":"../assets/Mercure.jpeg",
        "question":"En 1971, quel sport l'astronaute Alan Shepard a-t-il pratiqué sur la Lune pour tester la gravite ?",
        "answer1":"Le croquet",
        "answer2":"Le ping-pong",
        "answer3":"Le golf",
        "answer4":"Le foot",
        "goodAns":"Le golf",
        "behavior":0
    },
   {
        "num":6,
        "img":"../assets/Fontaine.jpg",
        "question":"Qui a prouvé que les planètes tournent autour du Soleil ?",
        "answer1":"Platon",
        "answer2":"Galilée",
        "answer3":"Nicolas Copernic",
        "answer4":"Isaac Newton",
        "goodAns":"Nicolas Copernic",
        "behavior":10
    },
    {
        "num":7,
        "img":"../assets/blackHole.jpg",
        "question":"Quelle est la planette la plus petite de notre système?",
        "answer1":"le soleil",
        "answer2":"Saturne",
        "answer3":"Mercure",
        "answer4":"Planète poulet ",
        "goodAns":"Mercure",
        "behavior":-5
    },
    {
        "num":8,
        "img":"../assets/saturn.jpg",
        "question":"Quelle est la galaxie la plus proche de la notre?",
        "answer1":"La voie Lactée",
        "answer2":"Shéhérazade",
        "answer3":"Andromède",
        "answer4":"Pouleiade",
        "goodAns":"Andromède",
        "behavior":0
    },
    {
        "num":9,
        "img":"../assets/neptune.jpg",
        "question":"De l'autre côté des trous noirs les scientifiques pensent trouver...",
        "answer1":"Dieu",
        "answer2":"Une fontaine blanche",
        "answer3":"Alain",
        "answer4":"42",
        "goodAns":"Une fontaine Blanche",
        "behavior":0
    },
    {
        "num":10,
        "img":"../assets/saturn.jpg",
        "question":"Chaque année la distance terre / lune change de ... ",
        "answer1":"-1.5 mètre",
        "answer2":"+3mètre",
        "answer3":"-2.1cm",
        "answer4":"+3.8cm",
        "goodAns":"+3.8cm",
        "behavior":0
    },
    {
        "num":11,
        "img":"../assets/blackHole.jpg",
        "question":"Dans notre galaxie il y a ...",
        "answer1":" Quelques millions de soleils",
        "answer2":"Quelques centaines de millions de soleils",
        "answer3":"Un Milliard de soleils",
        "answer4":"Des centaines de milliards de soleils",
        "goodAns":"Des centaines de milliards de soleils",
        "behavior":0
    },
    {
        "num":12,
        "img":"../assets/uranus.jpg",
        "question":"Jupiter est un corps céléste...",
        "answer1":"Gazeux",
        "answer2":"Rocheux",
        "answer3":"Aqueux",
        "answer4":" On ne sait pas, il manquait 1/4 d'heure de cuisson",
        "goodAns":"Gazeux",
        "behavior":0
    },
    {
        "num":13,
        "img":"../assets/Venus.jpg",
        "question":"Dû à sont effet de serre embalé, la température dur Venus est de...",
        "answer1":"829°c",
        "answer2":"460°c",
        "answer3":"ah! Les bonnes-femmes viennent de se liguer avec les écolos?!",
        "answer4":"128°c",
        "goodAns":"460°c",
        "behavior":0
    },
    {
        "num":14,
        "img":"../assets/saturn.jpg",
        "question":"Sur la lune la gravité est divisée par...",
        "answer1":"2",
        "answer2":"3",
        "answer3":"5",
        "answer4":"6",
        "goodAns":"6",
        "behavior":0
    },
    {
        "num":15,
        "img":"../assets/Mercure.jpeg",
        "question":"En partant du Soleil dans quel ordre rencontre -t-on ces planètes",
        "answer1":"Venus, Uranus, Neptune, Mercure",
        "answer2":"Jupiter, Terre, Mars, Saturne",
        "answer3":"Mars, Uranus, Neptune, Pluton",
        "answer4":"Ca dépend des orbites",
        "goodAns":"Mars, Uranus, Neptune, Pluton",
        "behavior":0
    },
    {
        "num":16,
        "img":"../assets/Fontaine.jpg",
        "question":" Si Abdou était une planète ce serait:",
        "answer1":"Mars",
        "answer2":"Venus",
        "answer3":"Poulet",
        "answer4":"Terre",
        "goodAns":"Poulet",
        "behavior":0
    },
    {
        "num":17,
        "img":"../assets/blackHole.jpg",
        "question":"Quelle planète du système solaire est la plus chaude ?",
        "answer1":"Mercure",
        "answer2":"Mars",
        "answer3":"Venus",
        "answer4":"Neptune",
        "goodAns":"Venus",
        "behavior":-6
    },
    {
        "num":18,
        "img":"../assets/jupiter.jpg",
        "question":"Quelle est la première nation à avoir envoyé un satellite dans l'espace?",
        "answer1":"Les français",
        "answer2":"Les américains",
        "answer3":"Les russes",
        "answer4":"Les chinois",
        "goodAns":"Les russes",
        "behavior":0
    },
    {
        "num":19,
        "img":"../assets/Mercure.jpeg",
        "question":"Quelle est la planète la plus lointaine du système solaire ?",
        "answer1":"Jupiter",
        "answer2":"Venus",
        "answer3":"Neptune",
        "answer4":"Saturne",
        "goodAns":"Neptune",
        "behavior":0
    },
    {
        "num":20,
        "img":"../assets/Mars.jpg",
        "question":"En quelle année l'homme a-t-il mis le pied sur la lune? ",
        "answer1":"1986",
        "answer2":"1969",
        "answer3":"1968",
        "answer4":"1792",
        "goodAns":"1969",
        "behavior":0
    },
    {
        "num":21,
        "img":"../assets/neptune.jpg",
        "question":"Quelle est la plus grande planète ?",
        "answer1":"La Terre",
        "answer2":"Venus",
        "answer3":"Pluton",
        "answer4":"Jupiter",
        "goodAns":"Jupiter",
        "behavior":0
    },
    {
        "num":22,
        "img":"../assets/terre.jpg",
        "question":"Bravo tu as rejoint notre bonne vieille terre ",
        "answer1":"Le poulet est content",
        "answer2":"il va pouvoir bouffer des graines",
        "answer3":"et nous on va pouvoir",
        "answer4":"bouffer le poulet!!!!",
        "goodAns":"",
        "behavior":0 
    }
]

